setup.py
hal/__init__.py
hal_json.egg-info/PKG-INFO
hal_json.egg-info/SOURCES.txt
hal_json.egg-info/dependency_links.txt
hal_json.egg-info/top_level.txt
hal_json.egg-info/zip-safe