Metadata-Version: 1.1
Name: hal-json
Version: 0.1
Summary: Parse and encode links according to RFC 5988 or HAL specs
Home-page: https://inean@github.com/inean/LinkHeader.git
Author: Michael Burrows, Carlos Martín
Author-email: inean.es@gmail.com
License: BSD
Keywords: RFC5988,HAL,json
Platform: UNKNOWN
Classifier: Development Status :: 3 - Alpha
Classifier: Intended Audience :: Developers
Classifier: License :: OSI Approved :: BSD License
Classifier: Programming Language :: Python :: 2
Classifier: Programming Language :: Python :: 3
Classifier: Topic :: Internet :: WWW/HTTP
Classifier: Topic :: Software Development :: Libraries :: Python Modules
